Workbook
Name Adesiv: [1]PARAMETROS!$E$40
Name Año: [1]PARAMETROS!$K$331
Name apell1: [1]PARAMETROS!$E$57
Name Bimestralmente: #REF!
Name C_100: [1]PARAMETROS!$C$99
Name C_104: [1]PARAMETROS!$C$103
Name C_108: [1]PARAMETROS!$C$107
Name C_112: [1]PARAMETROS!$C$111
Name C_116: [1]PARAMETROS!$C$115
Name C_120: [1]PARAMETROS!$C$119
Name C_124: [1]PARAMETROS!$C$123
Name C_128: [1]PARAMETROS!$C$127
Name C_132: [1]PARAMETROS!$C$131
Name C_136: [1]PARAMETROS!$C$135
Name C_140: [1]PARAMETROS!$C$139
Name C_149: [1]PARAMETROS!$C$148
Name C_153: [1]PARAMETROS!$C$152
Name C_157: [1]PARAMETROS!$C$156
Name C_161: [1]PARAMETROS!$C$160
Name C_165: [1]PARAMETROS!$C$164
Name C_169: [1]PARAMETROS!$C$168
Name C_173: [1]PARAMETROS!$C$172
Name C_177: [1]PARAMETROS!$C$176
Name C_181: [1]PARAMETROS!$C$180
Name C_289: [1]PARAMETROS!$C$288
Name C_293: [1]PARAMETROS!$C$292
Name C_299: [1]PARAMETROS!$C$298
Name C_303: [1]PARAMETROS!$C$302
Name C_307: [1]PARAMETROS!$C$306
Name C_315: [1]PARAMETROS!$C$310
Name C_316: [1]PARAMETROS!$C$311
Name C_320: [1]PARAMETROS!$C$315
Name C_321: [1]PARAMETROS!$C$316
Name C_325: [1]PARAMETROS!$C$320
Name C_84: [1]PARAMETROS!$C$83
Name C_88: [1]PARAMETROS!$C$87
Name C_92: [1]PARAMETROS!$C$91
Name C_96: [1]PARAMETROS!$C$95
Name CedDec: [1]PARAMETROS!$E$55
Name COD_DIR_SEC: [1]PARAMETROS!$M$33
Name CodRep: [1]PARAMETROS!$K$76
Name Conceptos: [2]Listas!$B$3:$B$27
Name Cuatrimestralmente: #REF!
Name dig_verf: [1]PARAMETROS!$I$17
Name DVDec: [1]PARAMETROS!$I$55
Name ExportarAExcel: #REF!
Name ExportarAExcel: #REF!
Name ExportarAExcel: #REF!
Name FCont: [1]PARAMETROS!$G$73
Name Mes: [1]PARAMETROS!$E$13
Name Nit: [1]PARAMETROS!$E$17
Name otrosnom: [1]PARAMETROS!$I$59
Name p_apellido: [1]PARAMETROS!$E$27
Name p_nombre: [1]PARAMETROS!$E$29
Name Periodo: #REF!
Name PerNatjud: [1]PARAMETROS!$L$22
Name R_28: [1]PARAMETROS!$T$90
Name R_29: [1]PARAMETROS!$T$94
Name R_30: [1]PARAMETROS!$T$98
Name R_31: [1]PARAMETROS!$T$102

Sheet Check List
C1: DSAB S.A.S
C2: NOMBRE DEL CLIENTE: | D2: Terminales De Graneles Liquidos Del Caribe
C3: NIT: | D3: 819002433-6
C4: TIPO DE TRABAJO: | D4: Revisoria fiscal
C5: FECHA DE VENCIMIENTO: | D5: 46248
C6: NOMBRE DEL PAPEL DE TRABAJO: | D6: Revisión Reteica
C7: PERIODO DE REVISIÓN: | D7: Julio
C8: NORMATIVIDAD APLICABLE: | D8: NIIF Plenas
C9: CIFRAS EXPRESADAS EN: | D9: Pesos colombianos
C10: ELABORADO POR: | D10: Carolina Hernández Rodríguez | F10: FECHA: | G10: 46247
C11: REVISADO POR: | D11: Robinson Romero | F11: FECHA: | G11: 46248
C12: REVISADO POR DIRECTOR: | F12: FECHA: | H12: Versión: 02 Fecha: 12/10/2020
B16: Información que se debe solicitar al cliente para preparar el Impuesto
B17: Revisión Retencion de Industria y Comercio Barrancabermeja
B18: 1 | C18: Balance de prueba periodo a revisar | E18: a
B19: 2 | C19: Borrador de la declaración de ICA
B20: 3 | C20: Certificados de retención de ICA que les practicaron | E20: x
B21: 4 | C21: Clasificar los bienes o servicios que la compañía vende en actividades sujetas, no sujetas, dentro y fuera del distrito, y si estos cumplen con la normatividad | E21: x
B22: 5 | C22: Libro auxiliar 2368 | E22: a
B23: 6 | C23: Libro auxiliar 135518 | E23: x
B24: 7 | C24: Pago mes de anterior | E24: x
B25: 8 | C25: Libro auxiliar de ingresos | E25: N/A
C28: Actividad economica 3315

Sheet DECLARACION
I2: ACTIVIDAD ECONOMICA | J2: TARIFA | K2: BASE GRAVABLE | L2: IMPUESTO
I3: 9609 | J3: 0.007 | K3: 188000 | L3: 1000
I4: 7490 | J4: 0.007 | K4: 5000000 | L4: =K4*J4 -> 35000
I5: 4669 | J5: 0.1 | K5: 3743000 | L5: 37000
I6: 5224 | J6: 0.1 | K6: 38966000 | L6: 390000
I7: 9903 | J7: 0.1 | K7: 1116000 | L7: 11000
K8: =SUM(K3:K7) -> 49013000 | L8: =SUM(L3:L7) -> 474000

Sheet Pago

Sheet REVISION ICA
B1: Entidad | D1: Terminales De Graneles Liquidos Del Caribe
B2: Papel de Trabajo | D2: Revisión Industria y Comercio
B3: Elaborado por: | D3: Carolina Hernández Rodríguez | F3: 46247
B4: Revisado por: | D4: Robinson Romero Manosalva | F4: 46248
B5: Periodo | D5: Julio
B6: Municipio | D6: Santa Marta
B8: CONCEPTO | C8: RENG | D8: AUDITORIA | F8: DECLARACION | H8: DIFERENCIA
B9: AUTORRETENEDOR | D9: BASE | E9: VALOR | F9: BASE | G9: VALOR | H9: BASE | I9: VALOR
A10: Acto oficial | B10: AUTORRETENCION POR FABRICACION (INDUSTRIAL) | C10: 1
B11: AUTORRETENCION POR COMERCIALIZACION | C11: 2 | K11: Cuenta | L11: Cuenta Descripción | M11: Debito | N11: Credito | O11: Saldo
B12: AUTORRETENCION POR SERVICIO | C12: 3 | K12: 2368010007 | L12: Impuest ICA Reten 7% | N12: =+BALANCE!I157 -> 36318 | O12: =ROUND(+N12-M12,-3) -> 36000
B13: AUTORRETENCION POR SERVICIOS FINANCIEROS Y BANCARIOS | C13: 4 | K13: 2368010010 | L13: Impuest ICA Rete 10% | N13: =+BALANCE!I159 -> 438243 | O13: =ROUND(+N13-M13,-3) -> 438000
B14: SUBTOTAL AUTORRETENCIONES (SUME RENGLONES 01+02+03+04) | C14: 5 | N14: =SUM(N12:N13) -> 474561 | O14: =SUM(O12:O13) -> 474000
B15: IMPUESTOS AVISOS Y TABLEROS (15% RENGLÓN 5) | C15: 6
B16: SOBRETASA BOMBERIL (3% RENGLON 5) | C16: 7 | K16: Retención | L16: % de retención | M16: Base de retención
B17: TOTAL SALDO A CARGO | C17: 8 | K17: 0.01 | L17: =+N13 -> 438243 | M17: =ROUND(+L17/K17,-3) -> 43824000
K18: 0.007 | L18: =+N12 -> 36318 | M18: =ROUND(+L18/K18,-3) -> 5188000
A19: pagos | B19: RETENCION POR COMPRA DE BIENES | C19: 9
B20: RETENCION POR SERVICIOS | C20: 10 | D20: =+M21 -> 49012000 | E20: =+O12+O13 -> 474000 | F20: =+DECLARACION!K8 -> 49013000 | G20: =+DECLARACION!L8 -> 474000 | H20: =+D20-F20 -> -1000 | I20: =+E20-G20 -> 0
B21: RETENCION POR TARJETA DEBITO Y CREDITO | C21: 11 | K21: =SUM(K17:K20) -> 0.017 | L21: Total | M21: =SUM(M17:M20) -> 49012000
B22: SUBTOTAL RETENCIONES PRACTICADAS | C22: 12
B23: TOTAL AUTORRETENCIONES Y RETENCIONES PRACTICADAS | C23: 13
B24: SANCIONES | C24: 14
B25: TOTAL SALDO A CARGO | C25: 15
B26: VALOR A PAGAR | C26: 16 | D26: =SUM(D20:D25) -> 49012000 | E26: =SUM(E20:E25) -> 474000 | F26: =SUM(F20:F25) -> 49013000 | G26: =SUM(G20:G25) -> 474000 | H26: =SUM(H20:H25) -> -1000 | I26: =SUM(I20:I25) -> 0
B27: INTERESES DE MORA | C27: 17
B28: TOTAL A PAGAR | C28: 18 | D28: =ROUND(+D26,-3) -> 49012000 | E28: =+E26+E27 -> 474000 | F28: 0 | G28: =+DECLARACION!J21 -> 0 | H28: =+D28-F28 -> 49012000 | I28: =+E28-G28 -> 474000
A30: Conclusión: De acuerdo con los procedimientos ejecutados a la fecha, evidenciamos que los valores reportados por retenciones de industria y comerio correspondientes al periodo en revision son integros y corresponden a las operaciones económicas ejecutadas durante el periodo de revisión.

Sheet BORRADOR TERLICA
B2: TERLICA S.A.S.
B3: DECLARACION RETE ICA
B4: AÑO | C4: 2026
B5: PERIODO | C5: 7
B6: ACTIVIDAD | C6: 3315
B9: RENGLON | C9: TARIFA % | D9: BASE | E9: IMPTO RTE ICA | G9: BASE | H9: RETEICA | J9: ACTIVIDAD
B10: B1 | C10: 2 | D10: =+ROUND(G10,-3) -> 0 | E10: =+ROUND(H10,-3) -> 0 | G10: =+H10/0.2*100 -> 0 | H10: 0
B11: B2 | C11: 5 | D11: =+ROUND(G11,-3) -> 0 | E11: =+ROUND(H11,-3) -> 0 | G11: =+H11/0.5*100 -> 0 | H11: 0 | I11: Compra de detergentes | J11: 4719 | K11: Comercio al por menor en establecimientos no especializados, con surtido compuesto principalmente por productos diferentes de alimentos (víveres en general), bebidas y tabaco.
B12: B2 | C12: 5 | D12: =+ROUND(G12,-3) -> 0 | E12: =+ROUND(H12,-3) -> 0 | G12: =+H12/0.5*100 -> 0 | I12: Construcción de edificios residenciales y no residencias a cambio de una retribucion o por contrata | J12: 4112 | K12: Construcción de edificios residenciales y no residencias a cambio de una retribucion o por contrata
B13: B3 | C13: 5 | D13: =+ROUND(G13,-3) -> 0 | E13: =+ROUND(H13,-3) -> 0 | G13: =+H13/0.5*100 -> 0 | H13: 0 | I13: Servicio comedor | J13: 5611
B14: B3 | C14: 5 | D14: =+ROUND(G14,-3) -> 0 | E14: =+ROUND(H14,-3) -> 0 | G14: =+H14/0.5*100 -> 0 | I14: Compras de materiales | J14: 4752 | K14: Comercio al por menor de artículos de ferretería, pinturas y productos de vidrio en establecimientos especializados.
B15: B4 | C15: 5 | D15: =+ROUND(G15,-3) -> 0 | E15: =+ROUND(H15,-3) -> 0 | G15: =+H15/0.5*100 -> 0 | H15: 0 | I15: Confeccion de prenda de vestir , expecto prendas de piel | J15: 1410
B16: B5 | C16: 7 | D16: =+ROUND(G16,-3) -> 188000 | E16: =+ROUND(H16,-3) -> 1000 | G16: =+H16/0.7*100 -> 188285.71 | H16: 1318 | I16: Estudio de seguridad | J16: 9609 | K16: 900392924
B17: B7 | C17: 7 | D17: =+ROUND(G17,-3) -> 5000000 | E17: =+ROUND(H17,-3) -> 35000 | F17: =+G17+G16 -> 5188285.7 | G17: =+H17/0.7*100 -> 5000000 | H17: 35000 | I17: Otras actividades profesionales científicas y técnicas n.c.p | J17: 7490 | K17: 901670478
B18: B5 | C18: 7 | D18: =+ROUND(G18,-3) -> 0 | E18: =+H18 -> 0 | G18: =+H18/0.7*100 -> 0 | H18: 0 | I18: Curso de control operativo
B19: B6 | C19: 8 | D19: =+ROUND(G19,-3) -> 0 | E19: =+H19 -> 0 | G19: =+H19/0.5*100 -> 0
B20: B7 | C20: 10 | D20: =+ROUND(G20,-3) -> 3743000 | E20: =+ROUND(H20,-3) -> 37000 | G20: =+H20/1*100 -> 3743000 | H20: 37430 | I20: Comercio al por mayor de otros productos n.c.p. | J20: 4669
B21: B7 | C21: 10 | D21: =+ROUND(G21,-3) -> 38966000 | E21: =+ROUND(H21,-3) -> 390000 | F21: =+G20+G21+G25 -> 43824300 | G21: =+H21/1*100 -> 38965700 | H21: 389657 | I21: Servicio de operación portuaria | J21: 5224 | K21: 800193573
B22: B7 | C22: 10 | D22: =+ROUND(G22,-3) -> 0 | E22: =+ROUND(H22,-3) -> 0 | G22: =+H22/1*100 -> 0 | H22: 0 | I22: Alquiler y arrendamiento de otros tipos de maquinaria, equipo y bienes tangibles | J22: 7730
B23: B7 | C23: 10 | D23: =+ROUND(G23,-3) -> 0 | E23: =+ROUND(H23,-3) -> 0 | G23: =+H23/1*100 -> 0 | I23: Comercio al por menor de otros productos nuevos en establecimientos especializados.-compra y mtto de manguera | J23: 4774
B24: B7 | C24: 10 | D24: =+ROUND(G24,-3) -> 0 | E24: =+ROUND(H24,-3) -> 0 | G24: =+H24/1*100 -> 0 | H24: 0 | I24: Servicio de transporte | J24: 4923
B25: B7 | C25: 10 | D25: =+ROUND(G25,-3) -> 1116000 | E25: =+ROUND(H25,-3) -> 11000 | G25: =+H25/1*100 -> 1115600 | H25: 11156 | I25: Otras actividades de Servicios | J25: 9903 | K25: 830028245
B26: B7 | C26: 10 | D26: =+ROUND(G26,-3) -> 0 | E26: =+ROUND(H26,-3) -> 0 | G26: =+H26/1*100 -> 0 | H26: 0 | I26: Mtt mueble | J26: 4669 | K26: 811033997
B27: B8 | C27: OTRAS
D28: =SUM(D10:D27) -> 49013000 | E28: =SUM(E10:E27) -> 474000 | G28: =G25*10% -> 111560 | H28: =SUM(H10:H27) -> 474561
B30: RENGLON | I30: 0
B31: 6 | C31: TOTAL PAGO O ABONO | E31: =+ROUND(D28,-3) -> 49013000 | H31: =+D47 -> 0
B32: 7 | C32: (-) PAG O AB EN CUENTA NO SUJ A RT ICA | E32: =+E31-D28 -> 0
B33: 8 | C33: TOTAL PAGO O ABONO SUJ A RTE IVA | E33: =+E31-E32 -> 49013000
B34: 9 | C34: (-) PAGO O AB SUJ RTE ICA FUERA | E34: =+ROUND(H34,-3) -> 0
B35: 10 | C35: TOTAL PAGO O ABONO EN CUENTA | E35: =+E33-E34 -> 49013000
B36: R 25 | C36: (-)RETENCIONES PRACTICADAS EN EXCESO O INDEBIDAS O POR OPERACIONES ANULADAS, RESCINDIDAS O RESUELTAS | E36: 0
B37: 11 | C37: VALOR RETENCIONES | E37: =+E28-E36 -> 474000
B38: 12 | C38: SANCIONES | E38: 0
B39: 13 | C39: TOTAL SALDO A PAGAR | E39: =+E37+E38 -> 474000
B40: GIRAR A NOMBRE DE ALCALDIA DE SANTA MARTA

Sheet BALANCE
B1: Terlica S.A.S. Saldos de cuentas de mayor Hora 12:13:04 Fecha 11.08.2026
B2: Santa Marta - Colombia Ledger OL RFSSLD00/AMANOTAS Página 1
B3: Períodos de arrastre 01-06 2026 Períodos informe 07-07 2026
B4: Soc. | C4: Cta.mayor | D4: Texto breve | E4: Mon. | F4: Arrastre de saldos | G4: Saldo per.anteriores | H4: Período de informe debe | I4: Saldo Haber per.inf. | J4: Saldo acumulado
B5: DA09 | C5: 1105100020 | D5: Cja Puerto | E5: COP | F5: 5000000 | G5: -1249580 | H5: 5206585 | I5: 3957005 | J5: 5000000
B6: DA09 | C6: 1105100120 | D6: Caja Menor Mtto Liz | E6: COP | F6: 5000000 | G6: 0 | H6: 1836700 | I6: 4545502 | J6: 2291198
B7: DA09 | C7: 1110050200 | D7: Bogot-081230 - extra | E7: COP | F7: 198964924 | G7: 392539367 | H7: 2817955450 | I7: 2598764194 | J7: 810695547
B8: DA09 | C8: 1110050201 | D8: Bogot-081230 -Cheque | E8: COP | F8: 0 | G8: 0 | H8: 9096538 | I8: 9096538 | J8: 0
B9: DA09 | C9: 1110050202 | D9: Bogot-081230 - consi | E9: COP | F9: 0 | G9: 0 | H9: 2817955450 | I9: 2817955450 | J9: 0
B10: DA09 | C10: 1110050203 | D10: Bogot-081230 - n/deb | E10: COP | F10: 0 | G10: 0 | H10: 314769753 | I10: 314769753 | J10: 0
B11: DA09 | C11: 1110050205 | D11: Bogot-081230 -transf | E11: COP | F11: 0 | G11: 0 | H11: 2439000918 | I11: 2239000918 | J11: 200000000
B12: DA09 | C12: 1110050300 | D12: Bogot-Rotativo-extra | E12: COP | F12: 483966271 | G12: -119613746 | H12: 391659624 | I12: 407489436 | J12: 348522713
B13: DA09 | C13: 1110050302 | D13: Bogot-Rotativo-consi | E13: COP | F13: 18691888006 | G13: 1551596012 | H13: 139833893 | I13: 0 | J13: 20383317911
B14: DA09 | C14: 1110050303 | D14: Bogot-Rotativo-N/deb | E14: COP | F14: -747576377 | G14: -28441078 | H14: 0 | I14: 4004081 | J14: -780021536
B15: DA09 | C15: 1110050304 | D15: Bogot-Rotativo-n/cre | E15: COP | F15: 4879706476 | G15: 0 | H15: 0 | I15: 0 | J15: 4879706476
B16: DA09 | C16: 1110050305 | D16: Bogot-Rotativo- Tran | E16: COP | F16: -23307984376 | G16: -1403541188 | H16: 0 | I16: 120000000 | J16: -24831525564
... B347: DA09 | C347: 9999999910 | D347: cuenta carga cta May | E347: COP | F347: 0 | G347: 0 | H347: 100255871 | I347: 100255871 | J347: 0
B348: DA09 | E348: COP | F348: 0 | G348: 0 | H348: 51919018897 | I348: 51919018897 | J348: 0
H349: =SUBTOTAL(9,H116:H348) -> 0 | I349: =SUBTOTAL(9,I116:I348) -> 474561 | J349: =I349-H349 -> 474561

Sheet AUX FISCAL
B3: Cta.mayor *
B4: Sociedad DA09
B5: Ledger OL
B6: Cuenta | C6: Texto breve | D6: Asignación | E6: Tercero | F6: Fecha doc. | G6: Fe.contab. | H6: Referencia | I6: Importe en ML | J6: Período | K6: Cla | L6: Nº doc. | M6: Texto | N6: Importe valorado ML2 | O6: Soc.
B7: 2368010007 | C7: Impuest ICA Reten 7% | D7: 901670478 | E7: JACH DESIGNS S.A.S. | F7: 01.07.2026 | G7: 01.07.2026 | H7: FE10 | I7: -35000 | J7: 7 | K7: RE | L7: 5100013869 | M7: REPARACION MALLA PERIMETRAL MIRADOR | N7: -10.17 | O7: DA09
B8: 2368010007 | C8: Impuest ICA Reten 7% | D8: 900392924 | E8: DARIO HERRERA G INVESTIGACIONE | F8: 10.07.2026 | G8: 21.07.2026 | H8: FE3177 | I8: -1318 | J8: 7 | K8: RE | L8: 5100013882 | M8: ESTUDIO DE VISITA DOMICILIARIA | N8: -0.4 | O8: DA09
B9: 2368010010 | C9: Impuest ICA Rete 10% | D9: 811033997 | E9: CDEM & CDEB S.A.S. | F9: 16.07.2026 | G9: 30.07.2026 | H9: FE338057 | I9: -11970 | J9: 7 | K9: RE | L9: 5100013930 | M9: COMPRA DE ESCUALIZADOR SURTIDOR GASOLI 1" | N9: -3.73 | O9: DA09
B10: 2368010010 | C10: Impuest ICA Rete 10% | D10: 830028245 | E10: EQUIS Y ZETA ESTRATEGIAS LTDA | F10: 06.07.2026 | G10: 10.07.2026 | H10: FEV21379 | I10: -11156 | J10: 7 | K10: RE | L10: 5100013868 | M10: FORTALECIMIENTO MARCA ELOGIA | N10: -3.38 | O10: DA09
B11: 2368010010 | C11: Impuest ICA Rete 10% | D11: 811033997 | E11: CDEM & CDEB S.A.S. | F11: 09.07.2026 | G11: 30.07.2026 | H11: FE338043 | I11: -25460 | J11: 7 | K11: RE | L11: 5100013927 | M11: REPARACION MANGUERA DE 6" | N11: -7.94 | O11: DA09
B12: 2368010010 | C12: Impuest ICA Rete 10% | D12: 800193573 | E12: SUPER PORTUARIA S.A.S | F12: 27.07.2026 | G12: 31.07.2026 | H12: 250528 | I12: -13542 | J12: 7 | K12: RE | L12: 5100013902 | M12: SERVICIOS DE OPERACION PORTUARIA | N12: -4.32 | O12: DA09
B13: 2368010010 | C13: Impuest ICA Rete 10% | D13: 800193573 | E13: SUPER PORTUARIA S.A.S | F13: 27.07.2026 | G13: 31.07.2026 | H13: 250529 | I13: -3564 | J13: 7 | K13: RE | L13: 5100013903 | M13: SERVICIOS DE OPERACION PORTUARIA | N13: -1.14 | O13: DA09
B14: 2368010010 | C14: Impuest ICA Rete 10% | D14: 800193573 | E14: SUPER PORTUARIA S.A.S | F14: 27.07.2026 | G14: 31.07.2026 | H14: 250530 | I14: -18296 | J14: 7 | K14: RE | L14: 5100013904 | M14: SERVICIOS DE OPERACION PORTUARIA | N14: -5.84 | O14: DA09
B15: 2368010010 | C15: Impuest ICA Rete 10% | D15: 800193573 | E15: SUPER PORTUARIA S.A.S | F15: 27.07.2026 | G15: 31.07.2026 | H15: 250531 | I15: -9133 | J15: 7 | K15: RE | L15: 5100013905 | M15: SERVICIOS DE OPERACION PORTUARIA | N15: -2.92 | O15: DA09
B16: 2368010010 | C16: Impuest ICA Rete 10% | D16: 800193573 | E16: SUPER PORTUARIA S.A.S | F16: 27.07.2026 | G16: 31.07.2026 | H16: 250526 | I16: -3457 | J16: 7 | K16: RE | L16: 5100013900 | M16: SERVICIOS DE OPERACION PORTUARIA | N16: -1.1 | O16: DA09
B17: 2368010010 | C17: Impuest ICA Rete 10% | D17: 800193573 | E17: SUPER PORTUARIA S.A.S | F17: 27.07.2026 | G17: 31.07.2026 | H17: 250527 | I17: -13435 | J17: 7 | K17: RE | L17: 5100013901 | M17: SERVICIOS DE OPERACION PORTUARIA | N17: -4.29 | O17: DA09
B18: 2368010010 | C18: Impuest ICA Rete 10% | D18: 800193573 | E18: SUPER PORTUARIA S.A.S | F18: 30.07.2026 | G18: 31.07.2026 | H18: 250553 | I18: -328230 | J18: 7 | K18: RE | L18: 5100013906 | M18: SERVICIOS DE OPERACION PORTUARIA | N18: -104.78 | O18: DA09
B19: TOTAL | I19: =SUM(I7:I18) -> -474561

Sheet Validación de facturas
B2: NOMBRE DEL CLIENTE: | C2: Terminales De Graneles Liquidos Del Caribe
B3: NIT: | C3: 819002433-6
B4: TIPO DE TRABAJO: | C4: Revisoria fiscal
B5: FECHA DE VENCIMIENTO: | C5: 46248
B6: NOMBRE DEL PAPEL DE TRABAJO: | C6: Revisión Reteica
B7: PERIODO DE REVISIÓN: | C7: Julio
B8: NORMATIVIDAD APLICABLE: | C8: NIIF Plenas
B9: CIFRAS EXPRESADAS EN: | C9: Pesos colombianos
B10: ELABORADO POR: | C10: Carolina Hernández Rodríguez | E10: FECHA: | F10: 46247
B11: REVISADO POR: | C11: Robinson Romero | E11: FECHA: | F11: 46248
B12: REVISADO POR DIRECTOR: | E12: FECHA: | G12: Versión: 02 Fecha: 12/10/2020
B14: OBJETIVO:
B15: Verificar la razonabilidad de los porcentajes de declaración de industria y comercio.
B17: PROCEDIMIENTO:
B18: 1. Solicitar 3 facturas de proveedores con mayor cuantía durante el periodo a revisar
B19: 2. Validar que las retención practicada sea correcta.
B20: 3. Documentar y concluir.
B22: DESARROLLO DE PROCEDIMIENTO:
B24: ** En la siguiente ruta se encuentra las facturas y causaciones de los comprobantes validados:
B26: Comprobante | C26: Factura | D26: Fecha | E26: Proveedor | F26: Concepto | G26: Base | H26: % de retención | I26: Cálculo de auditor | J26: Vr. Contable | K26: Diferencia
B27: 5100013869 | C27: FE10 | D27: 46199 | E27: JACH DESIGNS S.A.S. | F27: REPARACION MALLA PERIMETRAL MIRADOR | G27: 5000000 | H27: 0.007 | I27: =G27*H27 -> 35000 | J27: 35000 | K27: =+I27-J27 -> 0
B28: 5100013930 | C28: FE338057 | D28: 46219 | E28: CDEM & CDEB S.A.S. | F28: COMPRA DE ESCUALIZADOR SURTIDOR GASOLI 1" | G28: 1196993 | H28: 0.01 | I28: =G28*H28 -> 11969.93 | J28: 11970 | K28: =+I28-J28 -> -0.07
B29: 5100013904 | C29: 250530 | D29: 46230 | E29: SUPER PORTUARIA S.A.S | F29: SERVICIOS DE OPERACION PORTUARIA | G29: 1829605 | H29: 0.01 | I29: =G29*H29 -> 18296.05 | J29: 18296 | K29: =+I29-J29 -> 0.05
B32: Conclusión
B33: De acuerdo a los procedimientos de recalculo de retenciones realizados por el auditor, no se presentan diferencias en las facturas.

Sheet CUADRO RETEICA
B1: RETENCIÓN IVA COLOMBIA: TOTAL
B2: De 01.07.2026 A 31.07.2026
B3: DA09
B4: Acreedor | C4: Tp.rete | D4: Ret | E4: Importe en MD | F4: Impte.neto 2 MI | G4: Impte.base Qst en MI | H4: Importe qst en MI | I4: Impte.sin Qst MI
B5: 800193573 | C5: IS | D5: 37 | E5: 38965609 | F5: 38965609 | G5: 38965609 | H5: 389657 | I5: 0
B6: 811033997 | C6: IS | D6: 23 | E6: 4454161 | F6: 3742993 | G6: 3742993 | H6: 37430 | I6: 711168
B7: 830028245 | C7: IS | D7: 23 | E7: 1327594 | F7: 1115626 | G7: 1115626 | H7: 11156 | I7: 211968
B8: 900392924 | C8: IS | D8: 39 | E8: 224125 | F8: 188341 | G8: 188341 | H8: 1318 | I8: 35784
B9: 901670478 | C9: IS | D9: 39 | E9: 5950000 | F9: 5000000 | G9: 5000000 | H9: 35000 | I9: 950000
G10: =SUM(G5:G9) -> 49012569 | H10: =SUM(H5:H9) -> 474561
